hiphttp/__init__.py
hiphttp/hip.py
hiphttp-0.1.0.dist-info/METADATA
hiphttp-0.1.0.dist-info/WHEEL
hiphttp-0.1.0.dist-info/top_level.txt
hiphttp-0.1.0.dist-info/RECORD
