Metadata-Version: 2.1
Name: hiphttp
Version: 0.1.0
Summary: A very simple Http library
Home-page: UNKNOWN
Author: Muhammad Sesay
Author-email: UNKNOWN
License: MIT
Platform: UNKNOWN
